metaperson/__init__.py
metaperson/app/__init__.py
metaperson/app/onnx_to_trt.py
metaperson/app/person_detection_trt.py
metaperson/app/person_recognition_trt.py
metaperson/app/person_reid_trt.py
metaperson/model_zoo/__init__.py
metaperson/model_zoo/basetrack.py
metaperson/model_zoo/byte_tracker.py
metaperson/model_zoo/kalman_filter.py
metaperson/model_zoo/matching.py
metaperson/utils/__init__.py
metaperson/utils/boxes.py
metaperson/utils/trt.py
meta_person-3.4.18.dist-info/METADATA
meta_person-3.4.18.dist-info/WHEEL
meta_person-3.4.18.dist-info/top_level.txt
meta_person-3.4.18.dist-info/zip-safe
meta_person-3.4.18.dist-info/RECORD
